LICENSE
README.md
__version__.py
setup.cfg
setup.py
zflow.egg-info/PKG-INFO
zflow.egg-info/SOURCES.txt
zflow.egg-info/dependency_links.txt
zflow.egg-info/not-zip-safe
zflow.egg-info/top_level.txt