Metadata-Version: 2.1
Name: zflow
Version: 2.6.0
Summary: Zalando zflow installer
Home-page: https://github.bus.zalan.do/zai/zflow
Author: Zalando SE
Author-email: zflow-team@gmail.com
License: MIT license
Keywords: zflow
License-File: LICENSE
